{ "data" : [
    {
        "id": "1",
        "src": "lang.png",
        "menuId": "0"
    },
    {
        "id": "2",
        "src": "monkey.png",
        "menuId": "1"
    },
    {
        "id": "3",
        "src": "inst.png",
        "menuId": "3"
    },
    {
        "id": "4",
        "src": "bakudev.png",
        "menuId": "4"
    },
    {
        "id": "5",
        "src": "turk.png",
        "menuId": "0"
    },
    {
        "id": "6",
        "src": "million.png",
        "menuId": "2"
    }
] }